Workbook
Name aporte: APP!$D$17
Name patrimonio: APP!$D$20
Name qtd_anos: APP!$D$18
Name rendimento_carteira: APP!$D$13
Name salario: APP!$D$12
Name sugestao_investimento: APP!$D$14
Name taxa_mensal: APP!$D$19
Name tipo_perfil: APP!$C$32

Sheet APP
B11: CONFIGURAÇÕES
B12: Salário | D12: 2000
B13: Rendimento Carteira | D13: 0.009
B14: Sugestão de Investimento (30%) | D14: =D12*30% -> 600
B16: INVESTIMENTO MENSAL
B17: Quanto investir por mês ? | D17: 500
B18: Por Quantos Anos ? | D18: 5
B19: Taxa de Rendimento mensal ? | D19: 0.01079
B20: Patrimônio acumulado ? | D20: =FV(taxa_mensal,qtd_anos*12,aporte*-1) -> 41888.457
B21: Dividendos Mensais ? | D21: =patrimonio*rendimento_carteira -> 376.99611
B23: Cenários | D23: Dividendo
A24: 2 | B24: Quanto em 2 Anos ? | C24: =FV($D$19,$A24*12,aporte*-1) -> 13613.814 | D24: =C24*rendimento_carteira -> 122.52432
A25: 5 | B25: Quanto em 5 Anos ? | C25: =FV($D$19,$A25*12,aporte*-1) -> 41888.457 | D25: =C25*rendimento_carteira -> 376.99611
A26: 10 | B26: Quanto em 10 Anos ? | C26: =FV($D$19,$A26*12,aporte*-1) -> 121642.11 | D26: =C26*rendimento_carteira -> 1094.779
A27: 20 | B27: Quanto em 20 Anos ? | C27: =FV($D$19,$A27*12,aporte*-1) -> 562599.2 | D27: =C27*rendimento_carteira -> 5063.3928
A28: 30 | B28: Quanto em 30 Anos ? | C28: =FV($D$19,$A28*12,aporte*-1) -> 2161084.8 | D28: =C28*rendimento_carteira -> 19449.763
B32: PERFIL | C32: Agressivo
B33: VALOR A SER INVESTIDO POR MÊS | C33: =aporte -> 500
B35: TIPO DE FII | C35: Percentual Sugerido | D35: Valores
B36: PAPEL | C36: =VLOOKUP(tipo_perfil&"-"&B36,Planilha2!$A:$D,4,FALSE) -> 0.5 | D36: =C36*$C$33 -> 250
B37: TIJOLO | C37: =VLOOKUP(tipo_perfil&"-"&B37,Planilha2!$A:$D,4,FALSE) -> 0.1 | D37: =C37*$C$33 -> 50
B38: HÍBRIDOS | C38: =VLOOKUP(tipo_perfil&"-"&B38,Planilha2!$A:$D,4,FALSE) -> 0.05 | D38: =C38*$C$33 -> 25
B39: FOFs | C39: =VLOOKUP(tipo_perfil&"-"&B39,Planilha2!$A:$D,4,FALSE) -> 0.05 | D39: =C39*$C$33 -> 25
B40: DESENVOLVIMENTO | C40: =VLOOKUP(tipo_perfil&"-"&B40,Planilha2!$A:$D,4,FALSE) -> 0.2 | D40: =C40*$C$33 -> 100
B41: HOTELARIAS | C41: =VLOOKUP(tipo_perfil&"-"&B41,Planilha2!$A:$D,4,FALSE) -> 0.1 | D41: =C41*$C$33 -> 50
D42: =SUM(D36:D41) -> 500

Sheet Planilha2
G1: =B16&"-"&C16 -> Agressivo-TIJOLO | H1: =VLOOKUP(G1,$A:$D,4,FALSE) -> 0.1
A2: CHAVE | B2: PERFIL | C2: TIPO DE FII | D2: %
A3: =B3&"-"&C3 -> Conservador-PAPEL | B3: Conservador | C3: PAPEL | D3: 0.3 | H3: %
A4: =B4&"-"&C4 -> Conservador-TIJOLO | B4: Conservador | C4: TIJOLO | D4: 0.5 | G4: Moderado-TIJOLO | H4: =VLOOKUP(G4,$A:$D,4,FALSE) -> 0.35
A5: =B5&"-"&C5 -> Conservador-HÍBRIDOS | B5: Conservador | C5: HÍBRIDOS | D5: 0.1
A6: =B6&"-"&C6 -> Conservador-FOFs | B6: Conservador | C6: FOFs | D6: 0.1
A7: =B7&"-"&C7 -> Conservador-DESENVOLVIMENTO | B7: Conservador | C7: DESENVOLVIMENTO | D7: 0 | F7: Ideias para aprimorar:
A8: =B8&"-"&C8 -> Conservador-HOTELARIAS | B8: Conservador | C8: HOTELARIAS | D8: 0 | F8: Planejamento por caixinha
A9: =B9&"-"&C9 -> Moderado-PAPEL | B9: Moderado | C9: PAPEL | D9: 0.32 | F9: Planejamento por tipos de ações
A10: =B10&"-"&C10 -> Moderado-TIJOLO | B10: Moderado | C10: TIJOLO | D10: 0.35 | F10: Planejamento por férias
A11: =B11&"-"&C11 -> Moderado-HÍBRIDOS | B11: Moderado | C11: HÍBRIDOS | D11: 0.08
A12: =B12&"-"&C12 -> Moderado-FOFs | B12: Moderado | C12: FOFs | D12: 0.05
A13: =B13&"-"&C13 -> Moderado-DESENVOLVIMENTO | B13: Moderado | C13: DESENVOLVIMENTO | D13: 0.1
A14: =B14&"-"&C14 -> Moderado-HOTELARIAS | B14: Moderado | C14: HOTELARIAS | D14: 0.1
A15: =B15&"-"&C15 -> Agressivo-PAPEL | B15: Agressivo | C15: PAPEL | D15: 0.5
A16: =B16&"-"&C16 -> Agressivo-TIJOLO | B16: Agressivo | C16: TIJOLO | D16: 0.1
A17: =B17&"-"&C17 -> Agressivo-HÍBRIDOS | B17: Agressivo | C17: HÍBRIDOS | D17: 0.05
A18: =B18&"-"&C18 -> Agressivo-FOFs | B18: Agressivo | C18: FOFs | D18: 0.05
A19: =B19&"-"&C19 -> Agressivo-DESENVOLVIMENTO | B19: Agressivo | C19: DESENVOLVIMENTO | D19: 0.2
A20: =B20&"-"&C20 -> Agressivo-HOTELARIAS | B20: Agressivo | C20: HOTELARIAS | D20: 0.1
